jcmutils/__init__.py
jcmutils/dataset_utils.py
jcmutils/gen_sources.py
jcmutils/logger.py
jcmutils/solver.py
jcmutils-2.0.2.dist-info/LICENSE
jcmutils-2.0.2.dist-info/METADATA
jcmutils-2.0.2.dist-info/WHEEL
jcmutils-2.0.2.dist-info/top_level.txt
jcmutils-2.0.2.dist-info/RECORD
