Metadata-Version: 2.1
Name: jcmutils
Version: 2.0.2
Summary: A general utils for jcmsuite
Author: crafter-z
Author-email: crafterz@163.com
Keywords: jcmsuite,utils
Classifier: Programming Language :: Python :: 3
Classifier: License :: OSI Approved :: MIT License
Classifier: Operating System :: OS Independent
License-File: LICENSE
Requires-Dist: numpy
Requires-Dist: matplotlib
Requires-Dist: opencv-python
Requires-Dist: pyyaml
